<xml xmlns:v="urn:schemas-microsoft-com:vml"
 xmlns:o="urn:schemas-microsoft-com:office:office"
 xmlns:p="urn:schemas-microsoft-com:office:powerpoint">
 <o:shapelayout v:ext="edit">
  <o:idmap v:ext="edit" data="67"/>
 </o:shapelayout><p:shaperange id="_x0000_s32770">
  <v:rect id="_x0000_s32770" style='position:absolute;left:30pt;top:264pt;
   width:672pt;height:258pt;mso-wrap-style:none;v-text-anchor:middle' filled="f"
   fillcolor="#bbe0e3 [4]" strokecolor="fuchsia" strokeweight="3pt">
   <v:fill color2="white [0]"/>
   <v:shadow color="gray [2]"/>
  </v:rect><v:shapetype id="_x0000_t202" coordsize="21600,21600" o:spt="202"
   path="m0,0l0,21600,21600,21600,21600,0xe">
   <v:stroke joinstyle="miter"/>
   <v:path gradientshapeok="t" o:connecttype="rect"/>
  </v:shapetype><v:shape id="_x0000_s32771" type="#_x0000_t202" style='position:absolute;
   left:331.75pt;top:215.375pt;width:14.5pt;height:36pt' filled="f"
   fillcolor="#bbe0e3 [4]" stroked="f" strokecolor="black [1]">
   <v:fill color2="white [0]"/>
   <v:shadow color="gray [2]"/>
   <v:textbox style='mso-fit-shape-to-text:t'/>
  </v:shape><v:shape id="_x0000_s32772" type="#_x0000_t202" style='position:absolute;
   left:66pt;top:204pt;width:170.5pt;height:36pt;mso-wrap-style:none;
   v-text-anchor:top-baseline' filled="f" fillcolor="#bbe0e3 [4]" stroked="f"
   strokecolor="black [1]">
   <v:fill color2="white [0]"/>
   <v:shadow color="gray [2]"/>
   <v:textbox style='mso-fit-shape-to-text:t'/>
  </v:shape><v:rect id="_x0000_s32773" style='position:absolute;left:102pt;
   top:150pt;width:30pt;height:30pt;mso-wrap-style:none;v-text-anchor:middle'
   fillcolor="#963" strokecolor="black [1]">
   <v:shadow color="gray [2]"/>
  </v:rect><v:rect id="_x0000_s32774" style='position:absolute;left:132pt;
   top:150pt;width:30pt;height:30pt;mso-wrap-style:none;v-text-anchor:middle'
   fillcolor="#963" strokecolor="black [1]">
   <v:shadow color="gray [2]"/>
  </v:rect><v:rect id="_x0000_s32775" style='position:absolute;left:162pt;
   top:150pt;width:30pt;height:30pt;mso-wrap-style:none;v-text-anchor:middle'
   fillcolor="#963" strokecolor="black [1]">
   <v:shadow color="gray [2]"/>
  </v:rect><v:rect id="_x0000_s32776" style='position:absolute;left:102pt;
   top:120pt;width:30pt;height:30pt;mso-wrap-style:none;v-text-anchor:middle'
   fillcolor="#963" strokecolor="black [1]">
   <v:shadow color="gray [2]"/>
  </v:rect><v:rect id="_x0000_s32777" style='position:absolute;left:132pt;
   top:120pt;width:30pt;height:30pt;mso-wrap-style:none;v-text-anchor:middle'
   fillcolor="#963" strokecolor="black [1]">
   <v:shadow color="gray [2]"/>
  </v:rect><v:rect id="_x0000_s32778" style='position:absolute;left:162pt;
   top:90pt;width:30pt;height:30pt;mso-wrap-style:none;v-text-anchor:middle'
   fillcolor="#963" strokecolor="black [1]">
   <v:shadow color="gray [2]"/>
  </v:rect><v:rect id="_x0000_s32779" style='position:absolute;left:132pt;
   top:90pt;width:30pt;height:30pt;mso-wrap-style:none;v-text-anchor:middle'
   fillcolor="#963" strokecolor="black [1]">
   <v:shadow color="gray [2]"/>
  </v:rect><v:rect id="_x0000_s32780" style='position:absolute;left:102pt;
   top:90pt;width:30pt;height:30pt;mso-wrap-style:none;v-text-anchor:middle'
   fillcolor="#963" strokecolor="black [1]">
   <v:shadow color="gray [2]"/>
  </v:rect><v:rect id="_x0000_s32781" style='position:absolute;left:162pt;
   top:120pt;width:30pt;height:30pt;mso-wrap-style:none;v-text-anchor:middle'
   fillcolor="#963" strokecolor="black [1]">
   <v:shadow color="gray [2]"/>
  </v:rect><v:rect id="_x0000_s32782" style='position:absolute;left:132pt;
   top:60pt;width:30pt;height:30pt;mso-wrap-style:none;v-text-anchor:middle'
   fillcolor="#963" strokecolor="black [1]">
   <v:shadow color="gray [2]"/>
  </v:rect><v:rect id="_x0000_s32783" style='position:absolute;left:5in;top:120pt;
   width:30pt;height:30pt;mso-wrap-style:none;v-text-anchor:middle'
   fillcolor="fuchsia" strokecolor="black [1]">
   <v:shadow color="gray [2]"/>
  </v:rect><v:shape id="_x0000_s32784" type="#_x0000_t202" style='position:absolute;
   left:312pt;top:204pt;width:119.875pt;height:36pt;mso-wrap-style:none;
   v-text-anchor:top-baseline' filled="f" fillcolor="#bbe0e3 [4]" stroked="f"
   strokecolor="black [1]">
   <v:fill color2="white [0]"/>
   <v:shadow color="gray [2]"/>
   <v:textbox style='mso-fit-shape-to-text:t'/>
  </v:shape><v:rect id="_x0000_s32785" style='position:absolute;left:102pt;
   top:384pt;width:30pt;height:30pt;mso-wrap-style:none;v-text-anchor:middle'
   fillcolor="#963" strokecolor="black [1]">
   <v:shadow color="gray [2]"/>
  </v:rect><v:rect id="_x0000_s32786" style='position:absolute;left:132pt;
   top:384pt;width:30pt;height:30pt;mso-wrap-style:none;v-text-anchor:middle'
   fillcolor="#963" strokecolor="black [1]">
   <v:shadow color="gray [2]"/>
  </v:rect><v:rect id="_x0000_s32787" style='position:absolute;left:162pt;
   top:384pt;width:30pt;height:30pt;mso-wrap-style:none;v-text-anchor:middle'
   fillcolor="#963" strokecolor="black [1]">
   <v:shadow color="gray [2]"/>
  </v:rect><v:rect id="_x0000_s32788" style='position:absolute;left:102pt;
   top:354pt;width:30pt;height:30pt;mso-wrap-style:none;v-text-anchor:middle'
   fillcolor="#963" strokecolor="black [1]">
   <v:shadow color="gray [2]"/>
  </v:rect><v:rect id="_x0000_s32789" style='position:absolute;left:132pt;
   top:354pt;width:30pt;height:30pt;mso-wrap-style:none;v-text-anchor:middle'
   fillcolor="#963" strokecolor="black [1]">
   <v:shadow color="gray [2]"/>
  </v:rect><v:rect id="_x0000_s32790" style='position:absolute;left:162pt;
   top:324pt;width:30pt;height:30pt;mso-wrap-style:none;v-text-anchor:middle'
   fillcolor="#963" strokecolor="black [1]">
   <v:shadow color="gray [2]"/>
  </v:rect><v:rect id="_x0000_s32791" style='position:absolute;left:132pt;
   top:324pt;width:30pt;height:30pt;mso-wrap-style:none;v-text-anchor:middle'
   fillcolor="#963" strokecolor="black [1]">
   <v:shadow color="gray [2]"/>
  </v:rect><v:rect id="_x0000_s32792" style='position:absolute;left:102pt;
   top:324pt;width:30pt;height:30pt;mso-wrap-style:none;v-text-anchor:middle'
   fillcolor="#963" strokecolor="black [1]">
   <v:shadow color="gray [2]"/>
  </v:rect><v:rect id="_x0000_s32793" style='position:absolute;left:162pt;
   top:354pt;width:30pt;height:30pt;mso-wrap-style:none;v-text-anchor:middle'
   fillcolor="#963" strokecolor="black [1]">
   <v:shadow color="gray [2]"/>
  </v:rect><v:rect id="_x0000_s32794" style='position:absolute;left:132pt;
   top:294pt;width:30pt;height:30pt;mso-wrap-style:none;v-text-anchor:middle'
   fillcolor="#963" strokecolor="black [1]">
   <v:shadow color="gray [2]"/>
  </v:rect><v:rect id="_x0000_s32795" style='position:absolute;left:210pt;
   top:384pt;width:30pt;height:30pt;mso-wrap-style:none;v-text-anchor:middle'
   fillcolor="#963" strokecolor="black [1]">
   <v:shadow color="gray [2]"/>
  </v:rect><v:rect id="_x0000_s32796" style='position:absolute;left:240pt;
   top:384pt;width:30pt;height:30pt;mso-wrap-style:none;v-text-anchor:middle'
   fillcolor="#963" strokecolor="black [1]">
   <v:shadow color="gray [2]"/>
  </v:rect><v:rect id="_x0000_s32797" style='position:absolute;left:270pt;
   top:384pt;width:30pt;height:30pt;mso-wrap-style:none;v-text-anchor:middle'
   fillcolor="#963" strokecolor="black [1]">
   <v:shadow color="gray [2]"/>
  </v:rect><v:rect id="_x0000_s32798" style='position:absolute;left:210pt;
   top:354pt;width:30pt;height:30pt;mso-wrap-style:none;v-text-anchor:middle'
   fillcolor="#963" strokecolor="black [1]">
   <v:shadow color="gray [2]"/>
  </v:rect><v:rect id="_x0000_s32799" style='position:absolute;left:240pt;
   top:354pt;width:30pt;height:30pt;mso-wrap-style:none;v-text-anchor:middle'
   fillcolor="#963" strokecolor="black [1]">
   <v:shadow color="gray [2]"/>
  </v:rect><v:rect id="_x0000_s32800" style='position:absolute;left:270pt;
   top:324pt;width:30pt;height:30pt;mso-wrap-style:none;v-text-anchor:middle'
   fillcolor="#963" strokecolor="black [1]">
   <v:shadow color="gray [2]"/>
  </v:rect><v:rect id="_x0000_s32801" style='position:absolute;left:240pt;
   top:324pt;width:30pt;height:30pt;mso-wrap-style:none;v-text-anchor:middle'
   fillcolor="#963" strokecolor="black [1]">
   <v:shadow color="gray [2]"/>
  </v:rect><v:rect id="_x0000_s32802" style='position:absolute;left:210pt;
   top:324pt;width:30pt;height:30pt;mso-wrap-style:none;v-text-anchor:middle'
   fillcolor="#963" strokecolor="black [1]">
   <v:shadow color="gray [2]"/>
  </v:rect><v:rect id="_x0000_s32803" style='position:absolute;left:270pt;
   top:354pt;width:30pt;height:30pt;mso-wrap-style:none;v-text-anchor:middle'
   fillcolor="#963" strokecolor="black [1]">
   <v:shadow color="gray [2]"/>
  </v:rect><v:rect id="_x0000_s32804" style='position:absolute;left:240pt;
   top:4in;width:30pt;height:30pt;mso-wrap-style:none;v-text-anchor:middle'
   fillcolor="#963" strokecolor="black [1]">
   <v:shadow color="gray [2]"/>
  </v:rect><v:rect id="_x0000_s32805" style='position:absolute;left:546pt;
   top:168pt;width:30pt;height:30pt;mso-wrap-style:none;v-text-anchor:middle'
   fillcolor="#099 [6]" strokecolor="black [1]">
   <v:shadow color="gray [2]"/>
  </v:rect><v:rect id="_x0000_s32806" style='position:absolute;left:8in;top:168pt;
   width:30pt;height:30pt;mso-wrap-style:none;v-text-anchor:middle'
   fillcolor="#099 [6]" strokecolor="black [1]">
   <v:shadow color="gray [2]"/>
  </v:rect><v:rect id="_x0000_s32807" style='position:absolute;left:606pt;
   top:168pt;width:30pt;height:30pt;mso-wrap-style:none;v-text-anchor:middle'
   fillcolor="#099 [6]" strokecolor="black [1]">
   <v:shadow color="gray [2]"/>
  </v:rect><v:rect id="_x0000_s32808" style='position:absolute;left:546pt;
   top:138pt;width:30pt;height:30pt;mso-wrap-style:none;v-text-anchor:middle'
   fillcolor="#099 [6]" strokecolor="black [1]">
   <v:shadow color="gray [2]"/>
  </v:rect><v:rect id="_x0000_s32809" style='position:absolute;left:8in;top:138pt;
   width:30pt;height:30pt;mso-wrap-style:none;v-text-anchor:middle'
   fillcolor="#099 [6]" strokecolor="black [1]">
   <v:shadow color="gray [2]"/>
  </v:rect><v:rect id="_x0000_s32810" style='position:absolute;left:606pt;
   top:108pt;width:30pt;height:30pt;mso-wrap-style:none;v-text-anchor:middle'
   fillcolor="#099 [6]" strokecolor="black [1]">
   <v:shadow color="gray [2]"/>
  </v:rect><v:rect id="_x0000_s32811" style='position:absolute;left:8in;top:108pt;
   width:30pt;height:30pt;mso-wrap-style:none;v-text-anchor:middle'
   fillcolor="#099 [6]" strokecolor="black [1]">
   <v:shadow color="gray [2]"/>
  </v:rect><v:rect id="_x0000_s32812" style='position:absolute;left:546pt;
   top:108pt;width:30pt;height:30pt;mso-wrap-style:none;v-text-anchor:middle'
   fillcolor="#099 [6]" strokecolor="black [1]">
   <v:shadow color="gray [2]"/>
  </v:rect><v:rect id="_x0000_s32813" style='position:absolute;left:606pt;
   top:138pt;width:30pt;height:30pt;mso-wrap-style:none;v-text-anchor:middle'
   fillcolor="#099 [6]" strokecolor="black [1]">
   <v:shadow color="gray [2]"/>
  </v:rect><v:shape id="_x0000_s32814" type="#_x0000_t202" style='position:absolute;
   left:522pt;top:204pt;width:142.5pt;height:36pt;mso-wrap-style:none;
   v-text-anchor:top-baseline' filled="f" fillcolor="#bbe0e3 [4]" stroked="f"
   strokecolor="black [1]">
   <v:fill color2="white [0]"/>
   <v:shadow color="gray [2]"/>
   <v:textbox style='mso-fit-shape-to-text:t'/>
  </v:shape></p:shaperange>
 <p:shaperange id="_x0000_s32815">
  <v:line id="_x0000_s32815" style='position:absolute;flip:y;mso-wrap-style:none;
   v-text-anchor:middle' from="306pt,192pt" to="534pt,318pt" strokecolor="black [1]">
   <v:shadow color="gray [2]"/>
  </v:line><v:shape id="_x0000_s32816" type="#_x0000_t202" style='position:absolute;
   left:112.75pt;top:426pt;width:169.25pt;height:36pt;mso-wrap-style:none;
   v-text-anchor:top-baseline' filled="f" fillcolor="#bbe0e3 [4]" stroked="f"
   strokecolor="black [1]">
   <v:fill color2="white [0]"/>
   <v:shadow color="gray [2]"/>
   <v:textbox style='mso-fit-shape-to-text:t'/>
  </v:shape></p:shaperange>
 <p:shaperange id="_x0000_s32817">
  <v:rect id="_x0000_s32817" style='position:absolute;left:606pt;top:66pt;
   width:30pt;height:30pt;mso-wrap-style:none;v-text-anchor:middle'
   fillcolor="#099 [6]" strokecolor="black [1]">
   <v:shadow color="gray [2]"/>
  </v:rect><v:rect id="_x0000_s32818" style='position:absolute;left:8in;top:66pt;
   width:30pt;height:30pt;mso-wrap-style:none;v-text-anchor:middle'
   fillcolor="#099 [6]" strokecolor="black [1]">
   <v:shadow color="gray [2]"/>
  </v:rect><v:rect id="_x0000_s32819" style='position:absolute;left:546pt;
   top:66pt;width:30pt;height:30pt;mso-wrap-style:none;v-text-anchor:middle'
   fillcolor="#099 [6]" strokecolor="black [1]">
   <v:shadow color="gray [2]"/>
  </v:rect></p:shaperange>
 <p:shaperange id="_x0000_s32820">
  <v:rect id="_x0000_s32820" style='position:absolute;left:600pt;top:354pt;
   width:30pt;height:30pt;mso-wrap-style:none;v-text-anchor:middle'
   fillcolor="#099 [6]" strokecolor="black [1]">
   <v:shadow color="gray [2]"/>
  </v:rect><v:rect id="_x0000_s32821" style='position:absolute;left:570pt;
   top:354pt;width:30pt;height:30pt;mso-wrap-style:none;v-text-anchor:middle'
   fillcolor="#099 [6]" strokecolor="black [1]">
   <v:shadow color="gray [2]"/>
  </v:rect><v:rect id="_x0000_s32822" style='position:absolute;left:540pt;
   top:354pt;width:30pt;height:30pt;mso-wrap-style:none;v-text-anchor:middle'
   fillcolor="#099 [6]" strokecolor="black [1]">
   <v:shadow color="gray [2]"/>
  </v:rect><v:shape id="_x0000_s32823" type="#_x0000_t202" style='position:absolute;
   left:522pt;top:420pt;width:142.5pt;height:36pt;mso-wrap-style:none;
   v-text-anchor:top-baseline' filled="f" fillcolor="#bbe0e3 [4]" stroked="f"
   strokecolor="black [1]">
   <v:fill color2="white [0]"/>
   <v:shadow color="gray [2]"/>
   <v:textbox style='mso-fit-shape-to-text:t'/>
  </v:shape></p:shaperange>
 <p:shaperange id="_x0000_s32824">
  <v:line id="_x0000_s32824" style='position:absolute;flip:y;mso-wrap-style:none;
   v-text-anchor:middle' from="270pt,156pt" to="354pt,282pt" strokecolor="black [1]">
   <v:shadow color="gray [2]"/>
  </v:line><v:shape id="_x0000_s32825" type="#_x0000_t202" style='position:absolute;
   left:246pt;top:474pt;width:262.25pt;height:40.875pt' filled="f" fillcolor="#bbe0e3 [4]"
   stroked="f" strokecolor="black [1]">
   <v:fill color2="white [0]"/>
   <v:shadow color="gray [2]"/>
   <v:textbox style='mso-fit-shape-to-text:t'/>
  </v:shape><v:rect id="_x0000_s32826" style='position:absolute;left:30pt;
   top:18pt;width:672pt;height:240pt;mso-wrap-style:none;v-text-anchor:middle'
   filled="f" fillcolor="#bbe0e3 [4]" strokecolor="#963" strokeweight="3pt">
   <v:fill color2="white [0]"/>
   <v:shadow color="gray [2]"/>
  </v:rect><v:shape id="_x0000_s32827" type="#_x0000_t202" style='position:absolute;
   left:246pt;top:18pt;width:230.75pt;height:40.875pt;mso-wrap-style:none;
   v-text-anchor:top-baseline' filled="f" fillcolor="#bbe0e3 [4]" stroked="f"
   strokecolor="black [1]">
   <v:fill color2="white [0]"/>
   <v:shadow color="gray [2]"/>
   <v:textbox style='mso-fit-shape-to-text:t'/>
  </v:shape></p:shaperange>
</xml>