<xml xmlns:v="urn:schemas-microsoft-com:vml"
 xmlns:o="urn:schemas-microsoft-com:office:office"
 xmlns:p="urn:schemas-microsoft-com:office:powerpoint">
 <o:shapelayout v:ext="edit">
  <o:idmap v:ext="edit" data="9"/>
 </o:shapelayout><p:shaperange id="_x0000_s9218">
  <v:rect id="_x0000_s9218" style='position:absolute;left:30pt;top:264pt;
   width:672pt;height:258pt;mso-wrap-style:none;v-text-anchor:middle' filled="f"
   fillcolor="#bbe0e3 [4]" strokecolor="fuchsia" strokeweight="3pt">
   <v:fill color2="white [0]"/>
   <v:shadow color="gray [2]"/>
  </v:rect><v:shapetype id="_x0000_t202" coordsize="21600,21600" o:spt="202"
   path="m0,0l0,21600,21600,21600,21600,0xe">
   <v:stroke joinstyle="miter"/>
   <v:path gradientshapeok="t" o:connecttype="rect"/>
  </v:shapetype><v:shape id="_x0000_s9220" type="#_x0000_t202" style='position:absolute;
   left:331.75pt;top:215.375pt;width:14.5pt;height:36pt' filled="f"
   fillcolor="#bbe0e3 [4]" stroked="f" strokecolor="black [1]">
   <v:fill color2="white [0]"/>
   <v:shadow color="gray [2]"/>
   <v:textbox style='mso-fit-shape-to-text:t'/>
  </v:shape><v:shape id="_x0000_s9222" type="#_x0000_t202" style='position:absolute;
   left:66pt;top:204pt;width:170.625pt;height:36pt;mso-wrap-style:none;
   v-text-anchor:top-baseline' filled="f" fillcolor="#bbe0e3 [4]" stroked="f"
   strokecolor="black [1]">
   <v:fill color2="white [0]"/>
   <v:shadow color="gray [2]"/>
   <v:textbox style='mso-fit-shape-to-text:t'/>
  </v:shape><v:rect id="_x0000_s9223" style='position:absolute;left:102pt;
   top:150pt;width:30pt;height:30pt;mso-wrap-style:none;v-text-anchor:middle'
   fillcolor="#963" strokecolor="black [1]">
   <v:shadow color="gray [2]"/>
  </v:rect><v:rect id="_x0000_s9224" style='position:absolute;left:132pt;top:150pt;
   width:30pt;height:30pt;mso-wrap-style:none;v-text-anchor:middle'
   fillcolor="#963" strokecolor="black [1]">
   <v:shadow color="gray [2]"/>
  </v:rect><v:rect id="_x0000_s9225" style='position:absolute;left:162pt;top:150pt;
   width:30pt;height:30pt;mso-wrap-style:none;v-text-anchor:middle'
   fillcolor="#963" strokecolor="black [1]">
   <v:shadow color="gray [2]"/>
  </v:rect><v:rect id="_x0000_s9226" style='position:absolute;left:102pt;top:120pt;
   width:30pt;height:30pt;mso-wrap-style:none;v-text-anchor:middle'
   fillcolor="#963" strokecolor="black [1]">
   <v:shadow color="gray [2]"/>
  </v:rect><v:rect id="_x0000_s9227" style='position:absolute;left:132pt;top:120pt;
   width:30pt;height:30pt;mso-wrap-style:none;v-text-anchor:middle'
   fillcolor="#963" strokecolor="black [1]">
   <v:shadow color="gray [2]"/>
  </v:rect><v:rect id="_x0000_s9228" style='position:absolute;left:162pt;top:90pt;
   width:30pt;height:30pt;mso-wrap-style:none;v-text-anchor:middle'
   fillcolor="#963" strokecolor="black [1]">
   <v:shadow color="gray [2]"/>
  </v:rect><v:rect id="_x0000_s9229" style='position:absolute;left:132pt;top:90pt;
   width:30pt;height:30pt;mso-wrap-style:none;v-text-anchor:middle'
   fillcolor="#963" strokecolor="black [1]">
   <v:shadow color="gray [2]"/>
  </v:rect><v:rect id="_x0000_s9230" style='position:absolute;left:102pt;top:90pt;
   width:30pt;height:30pt;mso-wrap-style:none;v-text-anchor:middle'
   fillcolor="#963" strokecolor="black [1]">
   <v:shadow color="gray [2]"/>
  </v:rect><v:rect id="_x0000_s9231" style='position:absolute;left:162pt;top:120pt;
   width:30pt;height:30pt;mso-wrap-style:none;v-text-anchor:middle'
   fillcolor="#963" strokecolor="black [1]">
   <v:shadow color="gray [2]"/>
  </v:rect><v:rect id="_x0000_s9232" style='position:absolute;left:132pt;top:60pt;
   width:30pt;height:30pt;mso-wrap-style:none;v-text-anchor:middle'
   fillcolor="#963" strokecolor="black [1]">
   <v:shadow color="gray [2]"/>
  </v:rect><v:rect id="_x0000_s9233" style='position:absolute;left:5in;top:120pt;
   width:30pt;height:30pt;mso-wrap-style:none;v-text-anchor:middle'
   fillcolor="fuchsia" strokecolor="black [1]">
   <v:shadow color="gray [2]"/>
  </v:rect><v:shape id="_x0000_s9234" type="#_x0000_t202" style='position:absolute;
   left:312pt;top:204pt;width:119.875pt;height:36pt;mso-wrap-style:none;
   v-text-anchor:top-baseline' filled="f" fillcolor="#bbe0e3 [4]" stroked="f"
   strokecolor="black [1]">
   <v:fill color2="white [0]"/>
   <v:shadow color="gray [2]"/>
   <v:textbox style='mso-fit-shape-to-text:t'/>
  </v:shape><v:rect id="_x0000_s9235" style='position:absolute;left:102pt;
   top:384pt;width:30pt;height:30pt;mso-wrap-style:none;v-text-anchor:middle'
   fillcolor="#963" strokecolor="black [1]">
   <v:shadow color="gray [2]"/>
  </v:rect><v:rect id="_x0000_s9236" style='position:absolute;left:132pt;top:384pt;
   width:30pt;height:30pt;mso-wrap-style:none;v-text-anchor:middle'
   fillcolor="#963" strokecolor="black [1]">
   <v:shadow color="gray [2]"/>
  </v:rect><v:rect id="_x0000_s9237" style='position:absolute;left:162pt;top:384pt;
   width:30pt;height:30pt;mso-wrap-style:none;v-text-anchor:middle'
   fillcolor="#963" strokecolor="black [1]">
   <v:shadow color="gray [2]"/>
  </v:rect><v:rect id="_x0000_s9238" style='position:absolute;left:102pt;top:354pt;
   width:30pt;height:30pt;mso-wrap-style:none;v-text-anchor:middle'
   fillcolor="#963" strokecolor="black [1]">
   <v:shadow color="gray [2]"/>
  </v:rect><v:rect id="_x0000_s9239" style='position:absolute;left:132pt;top:354pt;
   width:30pt;height:30pt;mso-wrap-style:none;v-text-anchor:middle'
   fillcolor="#963" strokecolor="black [1]">
   <v:shadow color="gray [2]"/>
  </v:rect><v:rect id="_x0000_s9240" style='position:absolute;left:162pt;top:324pt;
   width:30pt;height:30pt;mso-wrap-style:none;v-text-anchor:middle'
   fillcolor="#963" strokecolor="black [1]">
   <v:shadow color="gray [2]"/>
  </v:rect><v:rect id="_x0000_s9241" style='position:absolute;left:132pt;top:324pt;
   width:30pt;height:30pt;mso-wrap-style:none;v-text-anchor:middle'
   fillcolor="#963" strokecolor="black [1]">
   <v:shadow color="gray [2]"/>
  </v:rect><v:rect id="_x0000_s9242" style='position:absolute;left:102pt;top:324pt;
   width:30pt;height:30pt;mso-wrap-style:none;v-text-anchor:middle'
   fillcolor="#963" strokecolor="black [1]">
   <v:shadow color="gray [2]"/>
  </v:rect><v:rect id="_x0000_s9243" style='position:absolute;left:162pt;top:354pt;
   width:30pt;height:30pt;mso-wrap-style:none;v-text-anchor:middle'
   fillcolor="#963" strokecolor="black [1]">
   <v:shadow color="gray [2]"/>
  </v:rect><v:rect id="_x0000_s9244" style='position:absolute;left:132pt;top:294pt;
   width:30pt;height:30pt;mso-wrap-style:none;v-text-anchor:middle'
   fillcolor="#963" strokecolor="black [1]">
   <v:shadow color="gray [2]"/>
  </v:rect><v:rect id="_x0000_s9245" style='position:absolute;left:210pt;top:384pt;
   width:30pt;height:30pt;mso-wrap-style:none;v-text-anchor:middle'
   fillcolor="#963" strokecolor="black [1]">
   <v:shadow color="gray [2]"/>
  </v:rect><v:rect id="_x0000_s9246" style='position:absolute;left:240pt;top:384pt;
   width:30pt;height:30pt;mso-wrap-style:none;v-text-anchor:middle'
   fillcolor="#963" strokecolor="black [1]">
   <v:shadow color="gray [2]"/>
  </v:rect><v:rect id="_x0000_s9247" style='position:absolute;left:270pt;top:384pt;
   width:30pt;height:30pt;mso-wrap-style:none;v-text-anchor:middle'
   fillcolor="#963" strokecolor="black [1]">
   <v:shadow color="gray [2]"/>
  </v:rect><v:rect id="_x0000_s9248" style='position:absolute;left:210pt;top:354pt;
   width:30pt;height:30pt;mso-wrap-style:none;v-text-anchor:middle'
   fillcolor="#963" strokecolor="black [1]">
   <v:shadow color="gray [2]"/>
  </v:rect><v:rect id="_x0000_s9249" style='position:absolute;left:240pt;top:354pt;
   width:30pt;height:30pt;mso-wrap-style:none;v-text-anchor:middle'
   fillcolor="#963" strokecolor="black [1]">
   <v:shadow color="gray [2]"/>
  </v:rect><v:rect id="_x0000_s9250" style='position:absolute;left:270pt;top:324pt;
   width:30pt;height:30pt;mso-wrap-style:none;v-text-anchor:middle'
   fillcolor="#963" strokecolor="black [1]">
   <v:shadow color="gray [2]"/>
  </v:rect><v:rect id="_x0000_s9251" style='position:absolute;left:240pt;top:324pt;
   width:30pt;height:30pt;mso-wrap-style:none;v-text-anchor:middle'
   fillcolor="#963" strokecolor="black [1]">
   <v:shadow color="gray [2]"/>
  </v:rect><v:rect id="_x0000_s9252" style='position:absolute;left:210pt;top:324pt;
   width:30pt;height:30pt;mso-wrap-style:none;v-text-anchor:middle'
   fillcolor="#963" strokecolor="black [1]">
   <v:shadow color="gray [2]"/>
  </v:rect><v:rect id="_x0000_s9253" style='position:absolute;left:270pt;top:354pt;
   width:30pt;height:30pt;mso-wrap-style:none;v-text-anchor:middle'
   fillcolor="#963" strokecolor="black [1]">
   <v:shadow color="gray [2]"/>
  </v:rect><v:rect id="_x0000_s9254" style='position:absolute;left:240pt;top:4in;
   width:30pt;height:30pt;mso-wrap-style:none;v-text-anchor:middle'
   fillcolor="#963" strokecolor="black [1]">
   <v:shadow color="gray [2]"/>
  </v:rect><v:rect id="_x0000_s9255" style='position:absolute;left:546pt;top:168pt;
   width:30pt;height:30pt;mso-wrap-style:none;v-text-anchor:middle'
   fillcolor="#099 [6]" strokecolor="black [1]">
   <v:shadow color="gray [2]"/>
  </v:rect><v:rect id="_x0000_s9256" style='position:absolute;left:8in;top:168pt;
   width:30pt;height:30pt;mso-wrap-style:none;v-text-anchor:middle'
   fillcolor="#099 [6]" strokecolor="black [1]">
   <v:shadow color="gray [2]"/>
  </v:rect><v:rect id="_x0000_s9257" style='position:absolute;left:606pt;top:168pt;
   width:30pt;height:30pt;mso-wrap-style:none;v-text-anchor:middle'
   fillcolor="#099 [6]" strokecolor="black [1]">
   <v:shadow color="gray [2]"/>
  </v:rect><v:rect id="_x0000_s9258" style='position:absolute;left:546pt;top:138pt;
   width:30pt;height:30pt;mso-wrap-style:none;v-text-anchor:middle'
   fillcolor="#099 [6]" strokecolor="black [1]">
   <v:shadow color="gray [2]"/>
  </v:rect><v:rect id="_x0000_s9259" style='position:absolute;left:8in;top:138pt;
   width:30pt;height:30pt;mso-wrap-style:none;v-text-anchor:middle'
   fillcolor="#099 [6]" strokecolor="black [1]">
   <v:shadow color="gray [2]"/>
  </v:rect><v:rect id="_x0000_s9260" style='position:absolute;left:606pt;top:108pt;
   width:30pt;height:30pt;mso-wrap-style:none;v-text-anchor:middle'
   fillcolor="#099 [6]" strokecolor="black [1]">
   <v:shadow color="gray [2]"/>
  </v:rect><v:rect id="_x0000_s9261" style='position:absolute;left:8in;top:108pt;
   width:30pt;height:30pt;mso-wrap-style:none;v-text-anchor:middle'
   fillcolor="#099 [6]" strokecolor="black [1]">
   <v:shadow color="gray [2]"/>
  </v:rect><v:rect id="_x0000_s9262" style='position:absolute;left:546pt;top:108pt;
   width:30pt;height:30pt;mso-wrap-style:none;v-text-anchor:middle'
   fillcolor="#099 [6]" strokecolor="black [1]">
   <v:shadow color="gray [2]"/>
  </v:rect><v:rect id="_x0000_s9263" style='position:absolute;left:606pt;top:138pt;
   width:30pt;height:30pt;mso-wrap-style:none;v-text-anchor:middle'
   fillcolor="#099 [6]" strokecolor="black [1]">
   <v:shadow color="gray [2]"/>
  </v:rect><v:shape id="_x0000_s9264" type="#_x0000_t202" style='position:absolute;
   left:522pt;top:204pt;width:142.625pt;height:36pt;mso-wrap-style:none;
   v-text-anchor:top-baseline' filled="f" fillcolor="#bbe0e3 [4]" stroked="f"
   strokecolor="black [1]">
   <v:fill color2="white [0]"/>
   <v:shadow color="gray [2]"/>
   <v:textbox style='mso-fit-shape-to-text:t'/>
  </v:shape></p:shaperange>
 <p:shaperange id="_x0000_s9265">
  <v:line id="_x0000_s9265" style='position:absolute;flip:y;mso-wrap-style:none;
   v-text-anchor:middle' from="306pt,192pt" to="534pt,318pt" strokecolor="black [1]">
   <v:shadow color="gray [2]"/>
  </v:line><v:shape id="_x0000_s9266" type="#_x0000_t202" style='position:absolute;
   left:112.75pt;top:426pt;width:169.25pt;height:36pt;mso-wrap-style:none;
   v-text-anchor:top-baseline' filled="f" fillcolor="#bbe0e3 [4]" stroked="f"
   strokecolor="black [1]">
   <v:fill color2="white [0]"/>
   <v:shadow color="gray [2]"/>
   <v:textbox style='mso-fit-shape-to-text:t'/>
  </v:shape></p:shaperange>
 <p:shaperange id="_x0000_s9267">
  <v:rect id="_x0000_s9267" style='position:absolute;left:606pt;top:66pt;
   width:30pt;height:30pt;mso-wrap-style:none;v-text-anchor:middle'
   fillcolor="#099 [6]" strokecolor="black [1]">
   <v:shadow color="gray [2]"/>
  </v:rect><v:rect id="_x0000_s9268" style='position:absolute;left:8in;top:66pt;
   width:30pt;height:30pt;mso-wrap-style:none;v-text-anchor:middle'
   fillcolor="#099 [6]" strokecolor="black [1]">
   <v:shadow color="gray [2]"/>
  </v:rect><v:rect id="_x0000_s9269" style='position:absolute;left:546pt;top:66pt;
   width:30pt;height:30pt;mso-wrap-style:none;v-text-anchor:middle'
   fillcolor="#099 [6]" strokecolor="black [1]">
   <v:shadow color="gray [2]"/>
  </v:rect></p:shaperange>
 <p:shaperange id="_x0000_s9270">
  <v:rect id="_x0000_s9270" style='position:absolute;left:600pt;top:354pt;
   width:30pt;height:30pt;mso-wrap-style:none;v-text-anchor:middle'
   fillcolor="#099 [6]" strokecolor="black [1]">
   <v:shadow color="gray [2]"/>
  </v:rect><v:rect id="_x0000_s9271" style='position:absolute;left:570pt;top:354pt;
   width:30pt;height:30pt;mso-wrap-style:none;v-text-anchor:middle'
   fillcolor="#099 [6]" strokecolor="black [1]">
   <v:shadow color="gray [2]"/>
  </v:rect><v:rect id="_x0000_s9272" style='position:absolute;left:540pt;top:354pt;
   width:30pt;height:30pt;mso-wrap-style:none;v-text-anchor:middle'
   fillcolor="#099 [6]" strokecolor="black [1]">
   <v:shadow color="gray [2]"/>
  </v:rect><v:shape id="_x0000_s9273" type="#_x0000_t202" style='position:absolute;
   left:522pt;top:420pt;width:142.625pt;height:36pt;mso-wrap-style:none;
   v-text-anchor:top-baseline' filled="f" fillcolor="#bbe0e3 [4]" stroked="f"
   strokecolor="black [1]">
   <v:fill color2="white [0]"/>
   <v:shadow color="gray [2]"/>
   <v:textbox style='mso-fit-shape-to-text:t'/>
  </v:shape></p:shaperange>
 <p:shaperange id="_x0000_s9274">
  <v:line id="_x0000_s9274" style='position:absolute;flip:y;mso-wrap-style:none;
   v-text-anchor:middle' from="270pt,156pt" to="354pt,282pt" strokecolor="black [1]">
   <v:shadow color="gray [2]"/>
  </v:line><v:shape id="_x0000_s9275" type="#_x0000_t202" style='position:absolute;
   left:246pt;top:474pt;width:262.25pt;height:40.875pt' filled="f" fillcolor="#bbe0e3 [4]"
   stroked="f" strokecolor="black [1]">
   <v:fill color2="white [0]"/>
   <v:shadow color="gray [2]"/>
   <v:textbox style='mso-fit-shape-to-text:t'/>
  </v:shape><v:rect id="_x0000_s9276" style='position:absolute;left:30pt;top:18pt;
   width:672pt;height:240pt;mso-wrap-style:none;v-text-anchor:middle' filled="f"
   fillcolor="#bbe0e3 [4]" strokecolor="#963" strokeweight="3pt">
   <v:fill color2="white [0]"/>
   <v:shadow color="gray [2]"/>
  </v:rect><v:shape id="_x0000_s9277" type="#_x0000_t202" style='position:absolute;
   left:246pt;top:18pt;width:231.125pt;height:40.875pt;mso-wrap-style:none;
   v-text-anchor:top-baseline' filled="f" fillcolor="#bbe0e3 [4]" stroked="f"
   strokecolor="black [1]">
   <v:fill color2="white [0]"/>
   <v:shadow color="gray [2]"/>
   <v:textbox style='mso-fit-shape-to-text:t'/>
  </v:shape></p:shaperange>
</xml>